text_colorized/__init__.py
text_colorized/console.py
TextColorized-0.0.1.dist-info/LICENSE.md
TextColorized-0.0.1.dist-info/METADATA
TextColorized-0.0.1.dist-info/WHEEL
TextColorized-0.0.1.dist-info/top_level.txt
TextColorized-0.0.1.dist-info/RECORD
